hippocampus/__init__.py
hippocampus-0.1.4.dist-info/METADATA
hippocampus-0.1.4.dist-info/WHEEL
hippocampus-0.1.4.dist-info/RECORD
