Metadata-Version: 2.1
Name: hippocampus
Version: 0.1.4
Summary: simple memoization with sqlite3 and expiry
Author: Pascal Jürgens
Author-email: juergens@uni-trier.de
Requires-Python: >=3.9,<4.0
Classifier: License :: OSI Approved :: MIT License
Classifier: Operating System :: OS Independent
Classifier: Programming Language :: Python :: 3
Classifier: Programming Language :: Python :: 3.9
Classifier: Programming Language :: Python :: 3.10
Classifier: Programming Language :: Python :: 3.11
Requires-Dist: dateparser (>=1.1.8,<2.0.0)
Requires-Dist: orjson (>=3.9.10,<4.0.0)
Requires-Dist: peewee (>=3.17.0,<4.0.0)
